phenomenon_interpreter/__init__.py
phenomenon_interpreter/main.py
phenomenon_interpreter/prompts.py
phenomenon_interpreter-2025.12.21230657.dist-info/METADATA
phenomenon_interpreter-2025.12.21230657.dist-info/WHEEL
phenomenon_interpreter-2025.12.21230657.dist-info/top_level.txt
phenomenon_interpreter-2025.12.21230657.dist-info/RECORD
