Metadata-Version: 2.4
Name: phenomenon-interpreter
Version: 2025.12.21230657
Summary: phenomenon-interpreter analyzes textual descriptions of natural events to generate structured summaries or classifications automatically
Author-email: phenomenon-interpreter <hi@eugene.plus>
License: MIT
Project-URL: Homepage, https://github.com/chigwell/phenomenon-interpreter
Requires-Python: >=3.9
Requires-Dist: langchain-llm7>=0.0.0
Requires-Dist: llmatch-messages>=0.0.0
Requires-Dist: langchain-core>=0.3.0
